odoo/addons/hr_expense_invoice/README.rst
odoo/addons/hr_expense_invoice/__init__.py
odoo/addons/hr_expense_invoice/__manifest__.py
odoo/addons/hr_expense_invoice/i18n/cs_CZ.po
odoo/addons/hr_expense_invoice/i18n/de.po
odoo/addons/hr_expense_invoice/i18n/es.po
odoo/addons/hr_expense_invoice/i18n/fr.po
odoo/addons/hr_expense_invoice/i18n/hr.po
odoo/addons/hr_expense_invoice/i18n/hr_expense_invoice.pot
odoo/addons/hr_expense_invoice/i18n/nl_NL.po
odoo/addons/hr_expense_invoice/i18n/pt.po
odoo/addons/hr_expense_invoice/i18n/pt_BR.po
odoo/addons/hr_expense_invoice/migrations/12.0.1.4.0/pre-migration.py
odoo/addons/hr_expense_invoice/models/__init__.py
odoo/addons/hr_expense_invoice/models/account_invoice.py
odoo/addons/hr_expense_invoice/models/account_move_line.py
odoo/addons/hr_expense_invoice/models/account_payment.py
odoo/addons/hr_expense_invoice/models/hr_expense.py
odoo/addons/hr_expense_invoice/models/hr_expense_sheet.py
odoo/addons/hr_expense_invoice/readme/CONTRIBUTORS.rst
odoo/addons/hr_expense_invoice/readme/DESCRIPTION.rst
odoo/addons/hr_expense_invoice/readme/ROADMAP.rst
odoo/addons/hr_expense_invoice/readme/USAGE.rst
odoo/addons/hr_expense_invoice/static/description/icon.png
odoo/addons/hr_expense_invoice/static/description/index.html
odoo/addons/hr_expense_invoice/tests/__init__.py
odoo/addons/hr_expense_invoice/tests/test_hr_expense_invoice.py
odoo/addons/hr_expense_invoice/views/hr_expense_views.xml
odoo12_addon_hr_expense_invoice-12.0.2.0.3.dist-info/METADATA
odoo12_addon_hr_expense_invoice-12.0.2.0.3.dist-info/WHEEL
odoo12_addon_hr_expense_invoice-12.0.2.0.3.dist-info/top_level.txt
odoo12_addon_hr_expense_invoice-12.0.2.0.3.dist-info/RECORD
